fpu/fmul.sv
`default_nettype none
module fmul (
    input  wire logic        clk,
    input  wire logic        rst_n,
    input  wire logic [31:0] input_a,
    input  wire logic [31:0] input_b,
    input  wire logic        input_valid,
    output logic [31:0]      result,
    output logic             out_valid
);

    logic        s1_sign_a, s1_sign_b;
    logic [7:0]  s1_exp_a, s1_exp_b;
    logic [23:0] s1_mant_a, s1_mant_b; 
    
    logic        c1_sign_res;
    logic [9:0]  c1_exp_temp; 
    logic [47:0] c1_mant_prod; 
    logic        c1_is_zero_or_sub;

    always_comb begin
        s1_sign_a = input_a[31];
        s1_sign_b = input_b[31];
        s1_exp_a  = input_a[30:23];
        s1_exp_b  = input_b[30:23];
        
        s1_mant_a = (s1_exp_a == 0) ? {1'b0, input_a[22:0]} : {1'b1, input_a[22:0]};
        s1_mant_b = (s1_exp_b == 0) ? {1'b0, input_b[22:0]} : {1'b1, input_b[22:0]};
        
        c1_is_zero_or_sub = (s1_exp_a == 0) || (s1_exp_b == 0);
        c1_sign_res = s1_sign_a ^ s1_sign_b;

        c1_exp_temp = {2'b0, s1_exp_a} + {2'b0, s1_exp_b} - 10'd127;

        c1_mant_prod = s1_mant_a * s1_mant_b;
    end

    logic        s1_sign_reg;
    logic [9:0]  s1_exp_reg;
    logic [47:0] s1_prod_reg;
    logic        s1_valid_reg;
    logic        s1_zero_reg;

    always_ff @(posedge clk) begin
        if (!rst_n) begin
            s1_sign_reg  <= '0;
            s1_exp_reg   <= '0;
            s1_prod_reg  <= '0;
            s1_valid_reg <= '0;
            s1_zero_reg  <= '0;
        end else begin
            s1_sign_reg  <= c1_sign_res;
            s1_exp_reg   <= c1_exp_temp;
            s1_prod_reg  <= c1_mant_prod;
            s1_valid_reg <= input_valid;
            s1_zero_reg  <= c1_is_zero_or_sub;
        end
    end

    logic [9:0]  c2_exp_adjusted;
    logic        c2_sticky;
    logic [26:0] c2_mant_norm;

    always_comb begin
        if (s1_prod_reg[47]) begin
            c2_exp_adjusted = s1_exp_reg + 1;
            c2_mant_norm = s1_prod_reg[46:20]; 
            c2_sticky    = |s1_prod_reg[19:0];
        end else begin
            c2_exp_adjusted = s1_exp_reg;
            c2_mant_norm = s1_prod_reg[45:19];
            c2_sticky    = |s1_prod_reg[18:0];
        end
    end

    logic        s2_sign_reg;
    logic [9:0]  s2_exp_reg;
    logic [26:0] s2_mant_reg;
    logic        s2_sticky_reg;
    logic        s2_valid_reg;
    logic        s2_zero_reg;

    always_ff @(posedge clk) begin
        if (!rst_n) begin
            s2_sign_reg   <= '0;
            s2_exp_reg    <= '0;
            s2_mant_reg   <= '0;
            s2_sticky_reg <= '0;
            s2_valid_reg  <= '0;
            s2_zero_reg   <= '0;
        end else begin
            s2_sign_reg   <= s1_sign_reg;
            s2_exp_reg    <= c2_exp_adjusted;
            s2_mant_reg   <= c2_mant_norm;
            s2_sticky_reg <= c2_sticky;
            s2_valid_reg  <= s1_valid_reg;
            s2_zero_reg   <= s1_zero_reg;
        end
    end


    logic [31:0] c3_result_comb;

    always_comb begin
        logic        guard, round, sticky, lsb;
        logic        round_up;
        logic [22:0] frac_final;
        logic [9:0]  exp_checked; 
        
        guard  = s2_mant_reg[3];
        round  = s2_mant_reg[2];
        sticky = s2_sticky_reg | s2_mant_reg[1] | s2_mant_reg[0];
        lsb    = s2_mant_reg[4]; 

        round_up = guard & (round | sticky | lsb);

        if (round_up) begin
            frac_final = s2_mant_reg[26:4] + 1;
            if (frac_final == 0) begin 
                exp_checked = s2_exp_reg + 1;
            end else begin
                exp_checked = s2_exp_reg;
            end
        end else begin
            frac_final = s2_mant_reg[26:4];
            exp_checked = s2_exp_reg;
        end

        if (s2_zero_reg || exp_checked[9]) begin 
            c3_result_comb = {s2_sign_reg, 31'b0};
        end else if (exp_checked >= 255) begin 
            c3_result_comb = {s2_sign_reg, 8'hFF, 23'b0};
        end else begin
            c3_result_comb = {s2_sign_reg, exp_checked[7:0], frac_final};
        end
    end

    always_ff @(posedge clk) begin
        if (!rst_n) begin
            result    <= '0;
            out_valid <= '0;
        end else begin
            result    <= c3_result_comb;
            out_valid <= s2_valid_reg;
        end
    end

endmodule

`default_nettype wire

fpu/fsqrt.sv
`default_nettype none

module fsqrt (
    input wire logic clk,
    input wire logic rst_n,
    input wire logic [31:0] input_a,
    input wire logic input_valid,
    output logic [31:0] result,
    output logic out_valid
);

(* ram_style = "block" *) reg [23:0] lut [0:1023];
(* ram_style = "block" *) reg [23:0] lut_sq [0:1023];

initial begin
  $readmemh("fsqrt_table.mem", lut);
  $readmemh("zero.mem", lut_sq);
end

/* verilator lint_off UNUSEDSIGNAL */
logic [23:0] delta_24;
logic [2:0] is_zero_reg;
logic [2:0] is_abnormal_reg;
logic [47:0] P_out;
logic [23:0] double_x1;
logic [7:0] exp_reg_plus;
/* verilator lint_on UNUSEDSIGNAL */
logic [2:0] valid_reg;

logic in_is_zero;
logic in_is_abnormal;

logic is_zero_final;
logic is_abnormal_final;

assign is_zero_final = is_zero_reg[1];
assign is_abnormal_final = is_abnormal_reg[1];
assign out_valid = valid_reg[2];

assign in_is_zero = (e_1 == 8'b0) && (m_1 == 23'b0);
assign in_is_abnormal = (e_1 == 8'b11111111);

always_ff @(posedge clk) begin // or negedge rst_n
  if (!rst_n) begin
    valid_reg <= 3'b000;
    is_abnormal_reg <= 3'b000;
    is_zero_reg <= 3'b000;
  end else begin
    valid_reg <= {valid_reg[1:0], input_valid};
    is_abnormal_reg <= {is_abnormal_reg[1:0], in_is_abnormal};
    is_zero_reg <= {is_zero_reg[1:0], in_is_zero}; 
  end
end

logic s_1;
logic [7:0] e_1;
logic [22:0] m_1;

logic [7:0] exp_out;
logic sign_out;

logic [23:0] a_fixed;
logic [23:0] x_0;
logic [23:0] x0_x0;
//logic [23:0] x_1;
logic [9:0] lut_addr;
assign lut_addr = {e_1[0], m_1[22:14]};

assign {s_1, e_1, m_1} = input_a; 

logic signed [8:0] e_wo_bias;
assign e_wo_bias = $signed({1'b0, e_1}) - 9'sd127;

always_ff @(posedge clk) begin
  x_0 <= lut[lut_addr];
  x0_x0 <= lut_sq[lut_addr];
end

always_ff @(posedge clk) begin//or negedge rst_n
  if (!rst_n) begin
    exp_out <= 8'b0;
    sign_out <= 1'b0;
    a_fixed <= 24'b0;
  end else begin
    exp_out <= 8'((e_wo_bias >>> 1) + 8'd127);
    sign_out <= s_1;
    if (e_1[0]) begin
      a_fixed <= {2'b01, m_1[22:1]};
    end else begin
      a_fixed <= {1'b1, m_1};
    end
  end
end


logic [23:0] a_x0_x0;
logic [23:0] a_x0;

always_comb begin
  a_x0_x0 = 24'((48'(a_fixed) * x0_x0) >> 24);
  a_x0 = 24'((48'(a_fixed) * x_0) >> 24);
end

logic [23:0] a_x0_reg;
logic signed [17:0] delta_reg; 
logic [7:0] exp_reg;
logic [7:0] exp_reg_minus;
logic sign_reg;

assign delta_24 = 24'h400000 - a_x0_x0;

always_ff @(posedge clk) begin //or negedge rst_n
  if (!rst_n) begin
    delta_reg <= 18'sb0;
    a_x0_reg <= 24'b0;
    exp_reg <= 8'b0;
    exp_reg_plus <= 8'b0;
    exp_reg_minus <= 8'b0;
    sign_reg <= 1'b0;
  end else begin
    delta_reg <= delta_24[17:0]; 

    a_x0_reg <= a_x0;
    exp_reg <= exp_out;
    exp_reg_plus <= exp_out + 8'd1;
    exp_reg_minus <= exp_out - 8'd1;
    sign_reg <= sign_out;
  end
end


logic signed [24:0] a_x0_signed;
logic signed [42:0] delta_mult;
logic [23:0] result_inner;
logic [7:0] exp_final;
logic [22:0] mant_final;

always_comb begin
  a_x0_signed = {1'b0, a_x0_reg};
  delta_mult = a_x0_signed * delta_reg;
  P_out = {1'b0, a_x0_reg, 1'b0, 1'b1, 21'b0} + 48'($signed(delta_mult));
  result_inner = P_out[45:22];

  if (result_inner[23]) begin
    exp_final = exp_reg;
    mant_final = result_inner[22:0];
  end else begin
    exp_final = exp_reg_minus;
    mant_final = {result_inner[21:0], 1'b0};
  end       
end

always_ff @(posedge clk) begin //or negedge rst_n
  if (!rst_n) begin
    result <= 32'b0;
  end else begin
    if (is_zero_final) begin
      result <= {sign_reg, 8'b0, 23'b0}; 
    end else if (is_abnormal_final) begin
      result <= {sign_reg, 8'hFF, 23'b0}; 
    end else begin
      result <= {sign_reg, exp_final, mant_final};
    end
  end
end
endmodule

`default_nettype wire

fpu/top_fmul_sqrt.sv
`default_nettype none

module top_fmul_sqrt (
    input  wire logic        clk,
    input  wire logic        rst_n,
    input  wire logic [31:0] a,           // fmul用の入力
    input  wire logic [31:0] b,           // fsqrt用の入力
    input  wire logic        input_valid, // 計算開始信号
    output      logic [31:0] result,      // a * sqrt(b)
    output      logic        out_valid    // 計算完了信号
);

    logic [31:0] sqrt_res;
    logic        sqrt_out_valid;

    // --- fsqrt インスタンス化 ---
    fsqrt u_fsqrt (
        .clk(clk),
        .rst_n(rst_n),
        .input_a(b),           // 入力bの平方根を求める
        .input_valid(input_valid),
        .result(sqrt_res),
        .out_valid(sqrt_out_valid)
    );

    // --- fmul インスタンス化 ---
    fmul u_fmul (
        .clk(clk),
        .rst_n(rst_n),
        .input_a(a),           // 入力a
        .input_b(sqrt_res),    // sqrt(b)の結果を入れる
        .input_valid(sqrt_out_valid), // sqrtが終わったらmulを開始
        .result(result),
        .out_valid(out_valid)
    );

endmodule

fpu/wave.vcd
$version Generated by VerilatedVcd $end
$timescale 1ps $end
 $scope module TOP $end
  $var wire 1 b clk $end
  $var wire 1 c rst_n $end
  $var wire 32 d a [31:0] $end
  $var wire 32 e b [31:0] $end
  $var wire 1 f input_valid $end
  $var wire 32 g result [31:0] $end
  $var wire 1 h out_valid $end
  $scope module top_fmul_sqrt $end
   $var wire 1 b clk $end
   $var wire 1 c rst_n $end
   $var wire 32 d a [31:0] $end
   $var wire 32 e b [31:0] $end
   $var wire 1 f input_valid $end
   $var wire 32 g result [31:0] $end
   $var wire 1 h out_valid $end
   $var wire 32 . sqrt_res [31:0] $end
   $var wire 1 / sqrt_out_valid $end
   $scope module u_fmul $end
    $var wire 1 b clk $end
    $var wire 1 c rst_n $end
    $var wire 32 d input_a [31:0] $end
    $var wire 32 . input_b [31:0] $end
    $var wire 1 / input_valid $end
    $var wire 32 g result [31:0] $end
    $var wire 1 h out_valid $end
    $var wire 1 # s1_sign_a $end
    $var wire 1 $ s1_sign_b $end
    $var wire 8 % s1_exp_a [7:0] $end
    $var wire 8 & s1_exp_b [7:0] $end
    $var wire 24 ' s1_mant_a [23:0] $end
    $var wire 24 ( s1_mant_b [23:0] $end
    $var wire 1 ) c1_sign_res $end
    $var wire 10 * c1_exp_temp [9:0] $end
    $var wire 48 + c1_mant_prod [47:0] $end
    $var wire 1 - c1_is_zero_or_sub $end
    $var wire 1 0 s1_sign_reg $end
    $var wire 10 1 s1_exp_reg [9:0] $end
    $var wire 48 2 s1_prod_reg [47:0] $end
    $var wire 1 4 s1_valid_reg $end
    $var wire 1 5 s1_zero_reg $end
    $var wire 10 6 c2_exp_adjusted [9:0] $end
    $var wire 1 7 c2_sticky $end
    $var wire 27 8 c2_mant_norm [26:0] $end
    $var wire 1 9 s2_sign_reg $end
    $var wire 10 : s2_exp_reg [9:0] $end
    $var wire 27 ; s2_mant_reg [26:0] $end
    $var wire 1 < s2_sticky_reg $end
    $var wire 1 = s2_valid_reg $end
    $var wire 1 > s2_zero_reg $end
    $var wire 32 ? c3_result_comb [31:0] $end
    $scope module unnamedblk1 $end
     $var wire 1 @ guard $end
     $var wire 1 A round $end
     $var wire 1 B sticky $end
     $var wire 1 C lsb $end
     $var wire 1 D round_up $end
     $var wire 23 E frac_final [22:0] $end
     $var wire 10 F exp_checked [9:0] $end
    $upscope $end
   $upscope $end
   $scope module u_fsqrt $end
    $var wire 1 b clk $end
    $var wire 1 c rst_n $end
    $var wire 32 e input_a [31:0] $end
    $var wire 1 f input_valid $end
    $var wire 32 . result [31:0] $end
    $var wire 1 / out_valid $end
    $var wire 24 G delta_24 [23:0] $end
    $var wire 3 H is_zero_reg [2:0] $end
    $var wire 3 I is_abnormal_reg [2:0] $end
    $var wire 48 J P_out [47:0] $end
    $var wire 24 p double_x1 [23:0] $end
    $var wire 8 L exp_reg_plus [7:0] $end
    $var wire 3 M valid_reg [2:0] $end
    $var wire 1 i in_is_zero $end
    $var wire 1 j in_is_abnormal $end
    $var wire 1 N is_zero_final $end
    $var wire 1 O is_abnormal_final $end
    $var wire 1 k s_1 $end
    $var wire 8 l e_1 [7:0] $end
    $var wire 23 m m_1 [22:0] $end
    $var wire 8 P exp_out [7:0] $end
    $var wire 1 Q sign_out $end
    $var wire 24 R a_fixed [23:0] $end
    $var wire 24 S x_0 [23:0] $end
    $var wire 24 T x0_x0 [23:0] $end
    $var wire 10 n lut_addr [9:0] $end
    $var wire 9 o e_wo_bias [8:0] $end
    $var wire 24 U a_x0_x0 [23:0] $end
    $var wire 24 V a_x0 [23:0] $end
    $var wire 24 W a_x0_reg [23:0] $end
    $var wire 18 X delta_reg [17:0] $end
    $var wire 8 Y exp_reg [7:0] $end
    $var wire 8 Z exp_reg_minus [7:0] $end
    $var wire 1 [ sign_reg $end
    $var wire 25 \ a_x0_signed [24:0] $end
    $var wire 43 ] delta_mult [42:0] $end
    $var wire 24 _ result_inner [23:0] $end
    $var wire 8 ` exp_final [7:0] $end
    $var wire 23 a mant_final [22:0] $end
   $upscope $end
  $upscope $end
 $upscope $end
$enddefinitions $end


#0
0#
0$
b00000000 %
b00000000 &
b000000000000000000000000 '
b000000000000000000000000 (
0)
b1110000001 *
b000000000000000000000000000000000000000000000000 +
1-
b00000000000000000000000000000000 .
0/
00
b0000000000 1
b000000000000000000000000000000000000000000000000 2
04
05
b0000000000 6
07
b000000000000000000000000000 8
09
b0000000000 :
b000000000000000000000000000 ;
0<
0=
0>
b00000000000000000000000000000000 ?
0@
0A
0B
0C
0D
b00000000000000000000000 E
b0000000000 F
b010000000000000000000000 G
b000 H
b000 I
b000000000000000000000000001000000000000000000000 J
b00000000 L
b000 M
0N
0O
b00000000 P
0Q
b000000000000000000000000 R
b000000000000000000000000 S
b000000000000000000000000 T
b000000000000000000000000 U
b000000000000000000000000 V
b000000000000000000000000 W
b000000000000000000 X
b00000000 Y
b00000000 Z
0[
b0000000000000000000000000 \
b0000000000000000000000000000000000000000000 ]
b000000000000000000000000 _
b00000000 `
b00000000000000000000000 a
0b
0c
b00000000000000000000000000000000 d
b00000000000000000000000000000000 e
0f
b00000000000000000000000000000000 g
0h
1i
0j
0k
b00000000 l
b00000000000000000000000 m
b0000000000 n
b110000001 o
b000000000000000000000000 p
#1
b101101001110111001010111 S
1b
#2
0b
#3
1b
#4
0b
#5
1b
#6
0b
#7
1b
#8
0b
#9
1b
#10
0b
1c
#11
b1110000001 1
15
b1110000001 6
b001 H
b00000001 L
b00111111 P
b100000000000000000000000 R
b010110100111011100101011 V
b11111111 Z
b11111111 `
1b
#12
b10011101 %
b100000000000000000000000 '
b0000011110 *
0b
b01001110100000000000000000000000 d
b00111111100000000000000000000000 e
1f
0i
b01111111 l
b1000000000 n
b000000000 o
#13
b11111111 &
b100000000000000000000000 (
b0100011101 *
b010000000000000000000000000000000000000000000000 +
0-
b01111111100000000000000000000000 .
b0000011110 1
b0000011110 6
b1110000001 :
1>
b1110000001 F
b010 H
b001011010011101110010101101000000000000000000000 J
b01000000 L
b001 M
1N
b01111111 P
b010000000000000000000000 R
b111111111110000000000110 S
b001111111111100000000001 V
b010110100111011100101011 W
b00111111 Y
b00111110 Z
b0010110100111011100101011 \
b101101001110111001010110 _
b00111111 `
b01101001110111001010110 a
1b
#14
0b
0f
#15
b00000000 &
b000000000000000000000000 (
b0000011110 *
b000000000000000000000000000000000000000000000000 +
1-
b00000000000000000000000000000000 .
b0100011101 1
b010000000000000000000000000000000000000000000000 2
05
b0100011101 6
b0000011110 :
b0000011110 F
b100 H
b000111111111110000000000101000000000000000000000 J
b10000000 L
b010 M
0N
b001111111111100000000001 W
b01111111 Y
b01111110 Z
b0001111111111100000000001 \
b011111111111000000000010 _
b01111110 `
b11111111110000000000100 a
1b
#16
0b
#17
b01111110 &
b111111111110000000000100 (
b0010011100 *
b011111111111000000000010000000000000000000000000 +
0-
b00111111011111111110000000000100 .
1/
b0000011110 1
b000000000000000000000000000000000000000000000000 2
15
b0000011110 6
b0100011101 :
0>
b01111111100000000000000000000000 ?
b0100011101 F
b000 H
b100 M
1b
#18
0b
#19
0/
b0010011100 1
b011111111111000000000010000000000000000000000000 2
14
05
b0010011100 6
b111111111100000000001000000 8
b0000011110 :
1>
b00000000000000000000000000000000 ?
b0000011110 F
b000 M
1b
b01111111100000000000000000000000 g
#20
0b
#21
04
b0010011100 :
b111111111100000000001000000 ;
1=
0>
b01001110011111111110000000000100 ?
b11111111110000000000100 E
b0010011100 F
1b
b00000000000000000000000000000000 g
#22
0b
#23
0=
1b
b01001110011111111110000000000100 g
1h
