fpu/fmul.sv
`default_nettype none
module fmul (
    input  wire logic        clk,
    input  wire logic        rst_n,
    input  wire logic [31:0] input_a,
    input  wire logic [31:0] input_b,
    input  wire logic        input_valid,
    output logic [31:0]      result,
    output logic             out_valid
);

    logic        s1_sign_a, s1_sign_b;
    logic [7:0]  s1_exp_a, s1_exp_b;
    logic [23:0] s1_mant_a, s1_mant_b; 
    
    logic        c1_sign_res;
    logic [9:0]  c1_exp_temp; 
    logic [47:0] c1_mant_prod; 
    logic        c1_is_zero_or_sub;

    always_comb begin
        s1_sign_a = input_a[31];
        s1_sign_b = input_b[31];
        s1_exp_a  = input_a[30:23];
        s1_exp_b  = input_b[30:23];
        
        s1_mant_a = (s1_exp_a == 0) ? {1'b0, input_a[22:0]} : {1'b1, input_a[22:0]};
        s1_mant_b = (s1_exp_b == 0) ? {1'b0, input_b[22:0]} : {1'b1, input_b[22:0]};
        
        c1_is_zero_or_sub = (s1_exp_a == 0) || (s1_exp_b == 0);
        c1_sign_res = s1_sign_a ^ s1_sign_b;

        c1_exp_temp = {2'b0, s1_exp_a} + {2'b0, s1_exp_b} - 10'd127;

        c1_mant_prod = s1_mant_a * s1_mant_b;
    end

    logic        s1_sign_reg;
    logic [9:0]  s1_exp_reg;
    logic [47:0] s1_prod_reg;
    logic        s1_valid_reg;
    logic        s1_zero_reg;

    always_ff @(posedge clk) begin
        if (!rst_n) begin
            s1_sign_reg  <= '0;
            s1_exp_reg   <= '0;
            s1_prod_reg  <= '0;
            s1_valid_reg <= '0;
            s1_zero_reg  <= '0;
        end else begin
            s1_sign_reg  <= c1_sign_res;
            s1_exp_reg   <= c1_exp_temp;
            s1_prod_reg  <= c1_mant_prod;
            s1_valid_reg <= input_valid;
            s1_zero_reg  <= c1_is_zero_or_sub;
        end
    end

    logic [9:0]  c2_exp_adjusted;
    logic        c2_sticky;
    logic [26:0] c2_mant_norm;

    always_comb begin
        if (s1_prod_reg[47]) begin
            c2_exp_adjusted = s1_exp_reg + 1;
            c2_mant_norm = s1_prod_reg[46:20]; 
            c2_sticky    = |s1_prod_reg[19:0];
        end else begin
            c2_exp_adjusted = s1_exp_reg;
            c2_mant_norm = s1_prod_reg[45:19];
            c2_sticky    = |s1_prod_reg[18:0];
        end
    end

    logic        s2_sign_reg;
    logic [9:0]  s2_exp_reg;
    logic [26:0] s2_mant_reg;
    logic        s2_sticky_reg;
    logic        s2_valid_reg;
    logic        s2_zero_reg;

    always_ff @(posedge clk) begin
        if (!rst_n) begin
            s2_sign_reg   <= '0;
            s2_exp_reg    <= '0;
            s2_mant_reg   <= '0;
            s2_sticky_reg <= '0;
            s2_valid_reg  <= '0;
            s2_zero_reg   <= '0;
        end else begin
            s2_sign_reg   <= s1_sign_reg;
            s2_exp_reg    <= c2_exp_adjusted;
            s2_mant_reg   <= c2_mant_norm;
            s2_sticky_reg <= c2_sticky;
            s2_valid_reg  <= s1_valid_reg;
            s2_zero_reg   <= s1_zero_reg;
        end
    end


    logic [31:0] c3_result_comb;

    always_comb begin
        logic        guard, round, sticky, lsb;
        logic        round_up;
        logic [22:0] frac_final;
        logic [9:0]  exp_checked; 
        
        guard  = s2_mant_reg[3];
        round  = s2_mant_reg[2];
        sticky = s2_sticky_reg | s2_mant_reg[1] | s2_mant_reg[0];
        lsb    = s2_mant_reg[4]; 

        round_up = guard & (round | sticky | lsb);

        if (round_up) begin
            frac_final = s2_mant_reg[26:4] + 1;
            if (frac_final == 0) begin 
                exp_checked = s2_exp_reg + 1;
            end else begin
                exp_checked = s2_exp_reg;
            end
        end else begin
            frac_final = s2_mant_reg[26:4];
            exp_checked = s2_exp_reg;
        end

        if (s2_zero_reg || exp_checked[9]) begin 
            c3_result_comb = {s2_sign_reg, 31'b0};
        end else if (exp_checked >= 255) begin 
            c3_result_comb = {s2_sign_reg, 8'hFF, 23'b0};
        end else begin
            c3_result_comb = {s2_sign_reg, exp_checked[7:0], frac_final};
        end
    end

    always_ff @(posedge clk) begin
        if (!rst_n) begin
            result    <= '0;
            out_valid <= '0;
        end else begin
            result    <= c3_result_comb;
            out_valid <= s2_valid_reg;
        end
    end

endmodule

`default_nettype wire

fpu/fsqrt.sv
`default_nettype none

module fsqrt (
    input wire logic clk,
    input wire logic rst_n,
    input wire logic [31:0] input_a,
    input wire logic input_valid,
    output logic [31:0] result,
    output logic out_valid
);

(* ram_style = "block" *) reg [23:0] lut [0:1023];
(* ram_style = "block" *) reg [23:0] lut_sq [0:1023];

initial begin
  $readmemh("fsqrt_table.hex", lut);
  for (int i = 0; i < 1024; i++) begin
    lut_sq[i] = 24'((48'(lut[i]) * lut[i]) >> 24);
  end
end

/* verilator lint_off UNUSEDSIGNAL */
logic [23:0] delta_24;
logic [2:0] is_zero_reg;
logic [2:0] is_abnormal_reg;
logic [47:0] P_out;
logic [23:0] double_x1;
logic [7:0] exp_reg_plus;
/* verilator lint_on UNUSEDSIGNAL */
logic [2:0] valid_reg;

logic in_is_zero;
logic in_is_abnormal;

logic is_zero_final;
logic is_abnormal_final;

assign is_zero_final = is_zero_reg[1];
assign is_abnormal_final = is_abnormal_reg[1];
assign out_valid = valid_reg[2];

assign in_is_zero = (e_1 == 8'b0) && (m_1 == 23'b0);
assign in_is_abnormal = (e_1 == 8'b11111111);

always_ff @(posedge clk or negedge rst_n) begin
  if (!rst_n) begin
    valid_reg <= 3'b000;
    is_abnormal_reg <= 3'b000;
    is_zero_reg <= 3'b000;
  end else begin
    valid_reg <= {valid_reg[1:0], input_valid};
    is_abnormal_reg <= {is_abnormal_reg[1:0], in_is_abnormal};
    is_zero_reg <= {is_zero_reg[1:0], in_is_zero}; 
  end
end

logic s_1;
logic [7:0] e_1;
logic [22:0] m_1;

logic [7:0] exp_out;
logic sign_out;

logic [23:0] a_fixed;
logic [23:0] x_0;
logic [23:0] x0_x0;
//logic [23:0] x_1;
logic [9:0] lut_addr;
assign lut_addr = {e_1[0], m_1[22:14]};

assign {s_1, e_1, m_1} = input_a; 

logic signed [8:0] e_wo_bias;
assign e_wo_bias = $signed({1'b0, e_1}) - 9'sd127;

always_ff @(posedge clk) begin
  x_0 <= lut[lut_addr];
  x0_x0 <= lut_sq[lut_addr];
end

always_ff @(posedge clk or negedge rst_n) begin
  if (!rst_n) begin
    exp_out <= 8'b0;
    sign_out <= 1'b0;
    a_fixed <= 24'b0;
  end else begin
    exp_out <= 8'((e_wo_bias >>> 1) + 8'd127);
    sign_out <= s_1;
    if (e_1[0]) begin
      a_fixed <= {2'b01, m_1[22:1]};
    end else begin
      a_fixed <= {1'b1, m_1};
    end
  end
end


logic [23:0] a_x0_x0;
logic [23:0] a_x0;

always_comb begin
  a_x0_x0 = 24'((48'(a_fixed) * x0_x0) >> 24);
  a_x0 = 24'((48'(a_fixed) * x_0) >> 24);
end

logic [23:0] a_x0_reg;
logic signed [17:0] delta_reg; 
logic [7:0] exp_reg;
logic [7:0] exp_reg_minus;
logic sign_reg;

assign delta_24 = 24'h400000 - a_x0_x0;

always_ff @(posedge clk or negedge rst_n) begin
  if (!rst_n) begin
    delta_reg <= 18'sb0;
    a_x0_reg <= 24'b0;
    exp_reg <= 8'b0;
    exp_reg_plus <= 8'b0;
    exp_reg_minus <= 8'b0;
    sign_reg <= 1'b0;
  end else begin
    delta_reg <= delta_24[17:0]; 

    a_x0_reg <= a_x0;
    exp_reg <= exp_out;
    exp_reg_plus <= exp_out + 8'd1;
    exp_reg_minus <= exp_out - 8'd1;
    sign_reg <= sign_out;
  end
end


logic signed [24:0] a_x0_signed;
logic signed [42:0] delta_mult;
logic [23:0] result_inner;
logic [7:0] exp_final;
logic [22:0] mant_final;

always_comb begin
  a_x0_signed = {1'b0, a_x0_reg};
  delta_mult = a_x0_signed * delta_reg;
  P_out = {1'b0, a_x0_reg, 1'b0, 1'b1, 21'b0} + 48'($signed(delta_mult));
  result_inner = P_out[45:22];

  if (result_inner[23]) begin
    exp_final = exp_reg;
    mant_final = result_inner[22:0];
  end else begin
    exp_final = exp_reg_minus;
    mant_final = {result_inner[21:0], 1'b0};
  end       
end

always_ff @(posedge clk or negedge rst_n) begin
  if (!rst_n) begin
    result <= 32'b0;
  end else begin
    if (is_zero_final) begin
      result <= {sign_reg, 8'b0, 23'b0}; 
    end else if (is_abnormal_final) begin
      result <= {sign_reg, 8'hFF, 23'b0}; 
    end else begin
      result <= {sign_reg, exp_final, mant_final};
    end
  end
end
endmodule

`default_nettype wire

fpu/top_fmul_sqrt.sv
`default_nettype none

module top_fmul_sqrt (
    input  wire logic        clk,
    input  wire logic        rst_n,
    input  wire logic [31:0] a,           // fmul用の入力
    input  wire logic [31:0] b,           // fsqrt用の入力
    input  wire logic        input_valid, // 計算開始信号
    output      logic [31:0] result,      // a * sqrt(b)
    output      logic        out_valid    // 計算完了信号
);

    logic [31:0] sqrt_res;
    logic        sqrt_out_valid;

    // --- fsqrt インスタンス化 ---
    fsqrt u_fsqrt (
        .clk(clk),
        .rst_n(rst_n),
        .input_a(b),           // 入力bの平方根を求める
        .input_valid(input_valid),
        .result(sqrt_res),
        .out_valid(sqrt_out_valid)
    );

    // --- fmul インスタンス化 ---
    fmul u_fmul (
        .clk(clk),
        .rst_n(rst_n),
        .input_a(a),           // 入力a
        .input_b(sqrt_res),    // sqrt(b)の結果を入れる
        .input_valid(sqrt_out_valid), // sqrtが終わったらmulを開始
        .result(result),
        .out_valid(out_valid)
    );

endmodule

fpu/wave.vcd
$version Generated by VerilatedVcd $end
$timescale 1ps $end
 $scope module TOP $end
  $var wire 1 c clk $end
  $var wire 1 d rst_n $end
  $var wire 32 e a [31:0] $end
  $var wire 32 f b [31:0] $end
  $var wire 1 g input_valid $end
  $var wire 32 h result [31:0] $end
  $var wire 1 i out_valid $end
  $scope module top_fmul_sqrt $end
   $var wire 1 c clk $end
   $var wire 1 d rst_n $end
   $var wire 32 e a [31:0] $end
   $var wire 32 f b [31:0] $end
   $var wire 1 g input_valid $end
   $var wire 32 h result [31:0] $end
   $var wire 1 i out_valid $end
   $var wire 32 / sqrt_res [31:0] $end
   $var wire 1 0 sqrt_out_valid $end
   $scope module u_fmul $end
    $var wire 1 c clk $end
    $var wire 1 d rst_n $end
    $var wire 32 e input_a [31:0] $end
    $var wire 32 / input_b [31:0] $end
    $var wire 1 0 input_valid $end
    $var wire 32 h result [31:0] $end
    $var wire 1 i out_valid $end
    $var wire 1 $ s1_sign_a $end
    $var wire 1 % s1_sign_b $end
    $var wire 8 & s1_exp_a [7:0] $end
    $var wire 8 ' s1_exp_b [7:0] $end
    $var wire 24 ( s1_mant_a [23:0] $end
    $var wire 24 ) s1_mant_b [23:0] $end
    $var wire 1 * c1_sign_res $end
    $var wire 10 + c1_exp_temp [9:0] $end
    $var wire 48 , c1_mant_prod [47:0] $end
    $var wire 1 . c1_is_zero_or_sub $end
    $var wire 1 1 s1_sign_reg $end
    $var wire 10 2 s1_exp_reg [9:0] $end
    $var wire 48 3 s1_prod_reg [47:0] $end
    $var wire 1 5 s1_valid_reg $end
    $var wire 1 6 s1_zero_reg $end
    $var wire 10 7 c2_exp_adjusted [9:0] $end
    $var wire 1 8 c2_sticky $end
    $var wire 27 9 c2_mant_norm [26:0] $end
    $var wire 1 : s2_sign_reg $end
    $var wire 10 ; s2_exp_reg [9:0] $end
    $var wire 27 < s2_mant_reg [26:0] $end
    $var wire 1 = s2_sticky_reg $end
    $var wire 1 > s2_valid_reg $end
    $var wire 1 ? s2_zero_reg $end
    $var wire 32 @ c3_result_comb [31:0] $end
    $scope module unnamedblk1 $end
     $var wire 1 A guard $end
     $var wire 1 B round $end
     $var wire 1 C sticky $end
     $var wire 1 D lsb $end
     $var wire 1 E round_up $end
     $var wire 23 F frac_final [22:0] $end
     $var wire 10 G exp_checked [9:0] $end
    $upscope $end
   $upscope $end
   $scope module u_fsqrt $end
    $var wire 1 c clk $end
    $var wire 1 d rst_n $end
    $var wire 32 f input_a [31:0] $end
    $var wire 1 g input_valid $end
    $var wire 32 / result [31:0] $end
    $var wire 1 0 out_valid $end
    $var wire 24 H delta_24 [23:0] $end
    $var wire 3 I is_zero_reg [2:0] $end
    $var wire 3 J is_abnormal_reg [2:0] $end
    $var wire 48 K P_out [47:0] $end
    $var wire 24 q double_x1 [23:0] $end
    $var wire 8 M exp_reg_plus [7:0] $end
    $var wire 3 N valid_reg [2:0] $end
    $var wire 1 j in_is_zero $end
    $var wire 1 k in_is_abnormal $end
    $var wire 1 O is_zero_final $end
    $var wire 1 P is_abnormal_final $end
    $var wire 1 l s_1 $end
    $var wire 8 m e_1 [7:0] $end
    $var wire 23 n m_1 [22:0] $end
    $var wire 8 Q exp_out [7:0] $end
    $var wire 1 R sign_out $end
    $var wire 24 S a_fixed [23:0] $end
    $var wire 24 T x_0 [23:0] $end
    $var wire 24 U x0_x0 [23:0] $end
    $var wire 10 o lut_addr [9:0] $end
    $var wire 9 p e_wo_bias [8:0] $end
    $var wire 24 V a_x0_x0 [23:0] $end
    $var wire 24 W a_x0 [23:0] $end
    $var wire 24 X a_x0_reg [23:0] $end
    $var wire 18 Y delta_reg [17:0] $end
    $var wire 8 Z exp_reg [7:0] $end
    $var wire 8 [ exp_reg_minus [7:0] $end
    $var wire 1 \ sign_reg $end
    $var wire 25 ] a_x0_signed [24:0] $end
    $var wire 43 ^ delta_mult [42:0] $end
    $var wire 24 ` result_inner [23:0] $end
    $var wire 8 a exp_final [7:0] $end
    $var wire 23 b mant_final [22:0] $end
    $scope module unnamedblk1 $end
     $var wire 32 # i [31:0] $end
    $upscope $end
   $upscope $end
  $upscope $end
 $upscope $end
$enddefinitions $end


#0
b00000000000000000000010000000000 #
0$
0%
b00000000 &
b00000000 '
b000000000000000000000000 (
b000000000000000000000000 )
0*
b1110000001 +
b000000000000000000000000000000000000000000000000 ,
1.
b00000000000000000000000000000000 /
00
01
b0000000000 2
b000000000000000000000000000000000000000000000000 3
05
06
b0000000000 7
08
b000000000000000000000000000 9
0:
b0000000000 ;
b000000000000000000000000000 <
0=
0>
0?
b00000000000000000000000000000000 @
0A
0B
0C
0D
0E
b00000000000000000000000 F
b0000000000 G
b010000000000000000000000 H
b000 I
b000 J
b000000000000000000000000001000000000000000000000 K
b00000000 M
b000 N
0O
0P
b00000000 Q
0R
b000000000000000000000000 S
b000000000000000000000000 T
b000000000000000000000000 U
b000000000000000000000000 V
b000000000000000000000000 W
b000000000000000000000000 X
b000000000000000000 Y
b00000000 Z
b00000000 [
0\
b0000000000000000000000000 ]
b0000000000000000000000000000000000000000000 ^
b000000000000000000000000 `
b00000000 a
b00000000000000000000000 b
0c
0d
b00000000000000000000000000000000 e
b00000000000000000000000000000000 f
0g
b00000000000000000000000000000000 h
0i
1j
0k
0l
b00000000 m
b00000000000000000000000 n
b0000000000 o
b110000001 p
b000000000000000000000000 q
#1
b101101001110111001010111 T
b011111111110000000001000 U
1c
#2
0c
#3
1c
#4
0c
#5
1c
#6
0c
#7
1c
#8
0c
#9
1c
#10
0c
1d
#11
b1110000001 2
16
b1110000001 7
b000000000000111111111100 H
b001 I
b00000001 M
b00111111 Q
b100000000000000000000000 S
b001111111111000000000100 V
b010110100111011100101011 W
b11111111 [
b11111111 a
1c
#12
b10011101 &
b100000000000000000000000 (
b0000011110 +
0c
b01001110100000000000000000000000 e
b00111111100000000000000000000000 f
1g
0j
b01111111 m
b1000000000 o
b000000000 p
#13
b11111111 '
b100000000000000000000000 )
b0100011101 +
b010000000000000000000000000000000000000000000000 ,
0.
b01111111100000000000000000000000 /
b0000011110 2
b0000011110 7
b1110000001 ;
1?
b1110000001 G
b000000000000111111111101 H
b010 I
b001011010100000100111011101010001101001101010100 K
b01000000 M
b001 N
1O
b01111111 Q
b010000000000000000000000 S
b111111111110000000000110 T
b111111111100000000001111 U
b001111111111000000000011 V
b001111111111100000000001 W
b010110100111011100101011 X
b000000111111111100 Y
b00111111 Z
b00111110 [
b0010110100111011100101011 ]
b0000000010110100110000010001101001101010100 ^
b101101010000010011101110 `
b00111111 a
b01101010000010011101110 b
1c
#14
0c
0g
#15
b00000000 '
b000000000000000000000000 )
b0000011110 +
b000000000000000000000000000000000000000000000000 ,
1.
b00000000000000000000000000000000 /
b0100011101 2
b010000000000000000000000000000000000000000000000 3
06
b0100011101 7
b0000011110 ;
b0000011110 G
b100 I
b000111111111111111111111011000000010011111111101 K
b10000000 M
b010 N
0O
b001111111111100000000001 X
b000000111111111101 Y
b01111111 Z
b01111110 [
b0001111111111100000000001 ]
b0000000001111111110110000000010011111111101 ^
b011111111111111111111101 `
b01111110 a
b11111111111111111111010 b
1c
#16
0c
#17
b01111110 '
b111111111111111111111010 )
b0010011100 +
b011111111111111111111101000000000000000000000000 ,
0.
b00111111011111111111111111111010 /
10
b0000011110 2
b000000000000000000000000000000000000000000000000 3
16
b0000011110 7
b0100011101 ;
0?
b01111111100000000000000000000000 @
b0100011101 G
b000 I
b100 N
1c
#18
0c
#19
00
b0010011100 2
b011111111111111111111101000000000000000000000000 3
15
06
b0010011100 7
b111111111111111111110100000 9
b0000011110 ;
1?
b00000000000000000000000000000000 @
b0000011110 G
b000 N
1c
b01111111100000000000000000000000 h
#20
0c
#21
05
b0010011100 ;
b111111111111111111110100000 <
1>
0?
b01001110011111111111111111111010 @
b11111111111111111111010 F
b0010011100 G
1c
b00000000000000000000000000000000 h
#22
0c
#23
0>
1c
b01001110011111111111111111111010 h
1i
